setup.py
bin/periscope
periscope/__init__.py
periscope/periscope.py
periscope/version.py
periscope.egg-info/PKG-INFO
periscope.egg-info/SOURCES.txt
periscope.egg-info/dependency_links.txt
periscope.egg-info/requires.txt
periscope.egg-info/top_level.txt
periscope/plugins/Addic7ed.py
periscope/plugins/BierDopje.py
periscope/plugins/OpenSubtitles.py
periscope/plugins/Podnapisi.py
periscope/plugins/Podnapisi2.py
periscope/plugins/SubScene.py
periscope/plugins/SubsWiki.py
periscope/plugins/SubtitleDatabase.py
periscope/plugins/SubtitleSource.py
periscope/plugins/Subtitulos.py
periscope/plugins/TheSubDB.py
periscope/plugins/TvSubtitles.py
periscope/plugins/__init__.py
periscope/plugins/test.py
periscope/plugins/unittests.py