Metadata-Version: 1.0
Name: periscope
Version: 0.2.1
Summary: Python module to download subtitles for a given video file
Home-page: http://code.google.com/p/periscope/
Author: Patrick Dessalle
Author-email: patrick.dessalle@gmail.com
License: GNU LGPL
Platform: UNKNOWN
